<Properties StartupConfiguration="{8E39E501-CD22-4D72-89D3-5C6DE2A6D30D}|Default">
  <MonoDevelop.Ide.Workbench ActiveDocument="CommitSize/Program.cs">
    <Files>
      <File FileName="CommitSize/Program.cs" Line="2" Column="2" />
    </Files>
    <Pads>
      <Pad Id="ProjectPad">
        <State name="__root__">
          <Node name="CommitSize" expanded="True">
            <Node name="CommitSize" expanded="True">
              <Node name="Program.cs" selected="True" />
            </Node>
          </Node>
        </State>
      </Pad>
    </Pads>
  </MonoDevelop.Ide.Workbench>
  <MonoDevelop.Ide.DebuggingService.PinnedWatches />
  <MonoDevelop.Ide.Workspace ActiveConfiguration="Debug" />
  <MonoDevelop.Ide.ItemProperties.CommitSize FirstBuild="True" PreferredExecutionTarget="MonoDevelop.Default" />
  <MonoDevelop.Ide.DebuggingService.Breakpoints>
    <BreakpointStore />
  </MonoDevelop.Ide.DebuggingService.Breakpoints>
  <MultiItemStartupConfigurations />
</Properties>